LICENSE
MANIFEST.in
README.md
setup.py
pacotepythonpro/__init__.py
pacotepythonpro/github_api.py
pacotepythonpro.egg-info/PKG-INFO
pacotepythonpro.egg-info/SOURCES.txt
pacotepythonpro.egg-info/dependency_links.txt
pacotepythonpro.egg-info/not-zip-safe
pacotepythonpro.egg-info/requires.txt
pacotepythonpro.egg-info/top_level.txt