Metadata-Version: 1.1
Name: pacotepythonpro
Version: 0.2
Summary: Módulo para exemplificar consturção de projetos python no curso PyTools
Home-page: https://github.com/vladimirmaciel/libpythonpro
Author: Vladimir Maciel 
Author-email: vladimirmaciel@gmail.com
License: GNU AFFERO GENERAL PUBLIC LICENSE
Platform: UNKNOWN
Classifier: Development Status :: 2 - Pre-Alpha
Classifier: Environment :: Console
Classifier: Intended Audience :: Developers
Classifier: License :: OSI Approved :: GNU Affero General Public License v3 or later (AGPLv3+)
Classifier: Operating System :: OS Independent
Classifier: Programming Language :: Python
Classifier: Programming Language :: Python :: 3.8
Classifier: Framework :: Pytest
